{
    "title": "CheerioCrawler Template",
    "type": "object",
    "schemaVersion": 1,
    "properties": {
        "scrapeMatchList": {
            "title": "Scrape list of matches",
            "type": "boolean",
            "description": "Actor will scrape matches for given leagues, seasons and season types",
            "default": false
        },
        "years": {
            "title": "Years to scrape",
            "type": "array",
            "description": "For sports, that have season partially in two years, use the year when season ends",
            "editor": "stringList",
            "prefill": ["2022"],
            "patternValue": "[0-9]{4}"
        },
        "seasonTypes": {
            "title": "Season types to scrape",
            "type": "array",
            "description": "Possible values: pre - Pre-season, reg - Regular season, post - Post-season (/Playoff), off - Off-season",
            "editor": "stringList",
            "prefill": ["reg", "post"],
            "patternValue": "(\\bpre\\b)|(\\breg\\b)|(\\bpost\\b)|(\\boff\\b)"
        },
        "leagues": {
            "title": "Leagues to scrape",
            "type": "array",
            "description": "Possible values: mlb, nhl, nba, wnba, nfl",
            "editor": "stringList",
            "prefill": ["mlb"],
            "patternValue": "(\\bmlb\\b)|(\\bnhl\\b)|(\\bnba\\b)|(\\bwnba\\b)|(\\bnfl\\b)"
        },
        "games": {
            "title": "Games to scrape",
            "type": "array",
            "description": "Either game ID (e.g. 401461551), or game URL (e.g. https://www.espn.com/nhl/game/_/gameId/401461551)",
            "editor": "stringList",
            "prefill": ["reg", "post"],
            "patternValue": "(\\bpre\\b)|(\\breg\\b)|(\\bpost\\b)|(\\boff\\b)"
        },
        "gameDetailsLeague": {
            "title": "League of games to scrape",
            "type": "string",
            "description": "Possible values: mlb, nhl, nba, wnba, nfl",
            "editor": "textfield",
            "prefill": "mlb",
            "pattern": "(\\bmlb\\b)|(\\bnhl\\b)|(\\bnba\\b)|(\\bwnba\\b)|(\\bnfl\\b)"
        }
    }
}
